toolsgen/__init__.py
toolsgen/cli.py
toolsgen/hf_hub.py
toolsgen/judge.py
toolsgen/problem_generator.py
toolsgen/prompts.py
toolsgen/schema.py
toolsgen/tool_caller.py
toolsgen/core/__init__.py
toolsgen/core/client.py
toolsgen/core/config.py
toolsgen/core/generator.py
toolsgen/core/io.py
toolsgen/core/parallel.py
toolsgen/core/record_builder.py
toolsgen/core/sequential.py
toolsgen/prompts/judge_system.txt
toolsgen/prompts/judge_user.txt
toolsgen/prompts/problem_generation_system.txt
toolsgen/prompts/problem_generation_user.txt
toolsgen/prompts/tool_caller_system.txt
toolsgen/sampling/__init__.py
toolsgen/sampling/batch.py
toolsgen/sampling/param_aware.py
toolsgen/sampling/random.py
toolsgen/sampling/semantic.py
toolsgen-0.5.1.dist-info/licenses/LICENSE
toolsgen-0.5.1.dist-info/METADATA
toolsgen-0.5.1.dist-info/WHEEL
toolsgen-0.5.1.dist-info/entry_points.txt
toolsgen-0.5.1.dist-info/top_level.txt
toolsgen-0.5.1.dist-info/RECORD
