Metadata-Version: 2.4
Name: toolsgen
Version: 0.5.1
Summary: Generate tool-calling datasets from OpenAI-compatible tool specs
Author: Ahmet Ataşoğlu
License: MIT
Project-URL: Homepage, https://github.com/atasoglu/toolsgen
Project-URL: Repository, https://github.com/atasoglu/toolsgen
Keywords: tools,dataset,llm,openai,tool-calling
Classifier: Programming Language :: Python :: 3
Classifier: Programming Language :: Python :: 3 :: Only
Classifier: Programming Language :: Python :: 3.9
Classifier: Programming Language :: Python :: 3.10
Classifier: Programming Language :: Python :: 3.11
Classifier: Programming Language :: Python :: 3.12
Classifier: Programming Language :: Python :: 3.13
Classifier: Programming Language :: Python :: 3.14
Classifier: License :: OSI Approved :: MIT License
Classifier: Operating System :: OS Independent
Requires-Python: >=3.9
License-File: LICENSE
Requires-Dist: pydantic>=2.7.0
Requires-Dist: openai>=1.50.0
Requires-Dist: tqdm>=4.66.0
Provides-Extra: hf
Requires-Dist: huggingface_hub>=0.20.0; extra == "hf"
Dynamic: license-file
